plotly_gif/__init__.py
plotly_gif/format_.py
plotly_gif/gif.py
plotly_gif/three_d_plots.py
plotly_gif/two_d_plots.py
plotly_gif-0.0.4.dist-info/LICENSE.txt
plotly_gif-0.0.4.dist-info/METADATA
plotly_gif-0.0.4.dist-info/WHEEL
plotly_gif-0.0.4.dist-info/top_level.txt
plotly_gif-0.0.4.dist-info/RECORD
