Metadata-Version: 2.1
Name: plotly-gif
Version: 0.0.4
Summary: Create gif from your plotly figures!
Home-page: https://github.com/dylanwal/plotly_gif
Author: Dylan Walsh
License: BSD
Platform: any
Classifier: License :: OSI Approved :: BSD License
Classifier: Programming Language :: Python :: 3
Classifier: Programming Language :: Python :: 3 :: Only
Classifier: Programming Language :: Python :: 3.7
Classifier: Programming Language :: Python :: 3.8
Classifier: Programming Language :: Python :: 3.9
Requires-Python: >=3.7
License-File: LICENSE.txt
Requires-Dist: Pillow (>=9.0.0)
Requires-Dist: plotly (>=5.5.0)
Requires-Dist: kaleido (>=0.2.1)
Requires-Dist: numpy (>=1.21.6)
